mgraph_ai_serverless/__init__.py
mgraph_ai_serverless/fast_api/MGraph_AI_Serverless__Fast_API.py
mgraph_ai_serverless/fast_api/__init__.py
mgraph_ai_serverless/fast_api/routes/Routes__Debug.py
mgraph_ai_serverless/fast_api/routes/Routes__Info.py
mgraph_ai_serverless/fast_api/routes/__init__.py
mgraph_ai_serverless/graph_engines/__init__.py
mgraph_ai_serverless/graph_engines/graphviz/Graphviz__Render.py
mgraph_ai_serverless/graph_engines/graphviz/__init__.py
mgraph_ai_serverless/graph_engines/graphviz/models/Model__Graphviz__Output_Format.py
mgraph_ai_serverless/graph_engines/graphviz/models/Model__Graphviz__Render_Dot.py
mgraph_ai_serverless/graph_engines/graphviz/models/__init__.py
mgraph_ai_serverless/graph_engines/graphviz/routes/Routes__Graphviz.py
mgraph_ai_serverless/graph_engines/graphviz/routes/__init__.py
mgraph_ai_serverless/graph_engines/matplotlib/MGraph__Export__Matplotlib.py
mgraph_ai_serverless/graph_engines/matplotlib/Matplotlib__Render.py
mgraph_ai_serverless/graph_engines/matplotlib/__init__.py
mgraph_ai_serverless/graph_engines/matplotlib/models/Model__Matplotlib__Output_Format.py
mgraph_ai_serverless/graph_engines/matplotlib/models/Model__Matplotlib__Render.py
mgraph_ai_serverless/graph_engines/matplotlib/models/__init__.py
mgraph_ai_serverless/graph_engines/matplotlib/routes/Routes__Matplotlib.py
mgraph_ai_serverless/graph_engines/matplotlib/routes/__init__.py
mgraph_ai_serverless/graph_engines/playwright/Playwright__Install_Check.py
mgraph_ai_serverless/graph_engines/playwright/Playwright__Serverless.py
mgraph_ai_serverless/graph_engines/playwright/__init__.py
mgraph_ai_serverless/graph_engines/playwright/flows/Flow__Playwright__Get_Page_Html.py
mgraph_ai_serverless/graph_engines/playwright/flows/Flow__Playwright__Get_Page_Pdf.py
mgraph_ai_serverless/graph_engines/playwright/flows/Flow__Playwright__Get_Page_Screenshot.py
mgraph_ai_serverless/graph_engines/playwright/flows/__init__.py
mgraph_ai_serverless-1.12.0.dist-info/LICENSE
mgraph_ai_serverless-1.12.0.dist-info/METADATA
mgraph_ai_serverless-1.12.0.dist-info/WHEEL
mgraph_ai_serverless-1.12.0.dist-info/RECORD
