Metadata-Version: 2.3
Name: mgraph_ai_serverless
Version: 1.12.0
Summary: MGraph-AI - Serverless
License: Apache 2.0
Author: Dinis Cruz
Author-email: dinis.cruz@owasp.org
Requires-Python: >=3.11,<4.0
Classifier: License :: Other/Proprietary License
Classifier: Programming Language :: Python :: 3
Classifier: Programming Language :: Python :: 3.11
Classifier: Programming Language :: Python :: 3.12
Classifier: Programming Language :: Python :: 3.13
Requires-Dist: graphviz
Requires-Dist: httpx
Requires-Dist: mangum
Requires-Dist: matplotlib
Requires-Dist: mgraph-ai
Requires-Dist: networkx
Requires-Dist: osbot-aws
Requires-Dist: osbot-fast-api
Requires-Dist: osbot-playwright
Requires-Dist: osbot-utils
Requires-Dist: uvicorn
Project-URL: Homepage, https://github.com/owasp-sbot/MGraph-AI-Serverless
Project-URL: Repository, https://github.com/owasp-sbot/MGraph-AI-Serverless
